{
  "PUT - Update User" : {
    "transaction" : "PUT - Update User",
    "sampleCount" : 1,
    "errorCount" : 0,
    "errorPct" : 0.0,
    "meanResTime" : 285.0,
    "medianResTime" : 285.0,
    "minResTime" : 285.0,
    "maxResTime" : 285.0,
    "pct1ResTime" : 285.0,
    "pct2ResTime" : 285.0,
    "pct3ResTime" : 285.0,
    "throughput" : 3.5087719298245617,
    "receivedKBytesPerSec" : 3.76233552631579,
    "sentKBytesPerSec" : 0.9354440789473685
  },
  "DELETE - User" : {
    "transaction" : "DELETE - User",
    "sampleCount" : 1,
    "errorCount" : 0,
    "errorPct" : 0.0,
    "meanResTime" : 247.0,
    "medianResTime" : 247.0,
    "minResTime" : 247.0,
    "maxResTime" : 247.0,
    "pct1ResTime" : 247.0,
    "pct2ResTime" : 247.0,
    "pct3ResTime" : 247.0,
    "throughput" : 4.048582995951417,
    "receivedKBytesPerSec" : 3.949740637651822,
    "sentKBytesPerSec" : 0.8223684210526316
  },
  "GET - List Users" : {
    "transaction" : "GET - List Users",
    "sampleCount" : 1,
    "errorCount" : 0,
    "errorPct" : 0.0,
    "meanResTime" : 1392.0,
    "medianResTime" : 1392.0,
    "minResTime" : 1392.0,
    "maxResTime" : 1392.0,
    "pct1ResTime" : 1392.0,
    "pct2ResTime" : 1392.0,
    "pct3ResTime" : 1392.0,
    "throughput" : 0.7183908045977011,
    "receivedKBytesPerSec" : 1.515355603448276,
    "sentKBytesPerSec" : 0.085589529454023
  },
  "POST - Create User" : {
    "transaction" : "POST - Create User",
    "sampleCount" : 1,
    "errorCount" : 0,
    "errorPct" : 0.0,
    "meanResTime" : 243.0,
    "medianResTime" : 243.0,
    "minResTime" : 243.0,
    "maxResTime" : 243.0,
    "pct1ResTime" : 243.0,
    "pct2ResTime" : 243.0,
    "pct3ResTime" : 243.0,
    "throughput" : 4.11522633744856,
    "receivedKBytesPerSec" : 4.460841049382716,
    "sentKBytesPerSec" : 0.9765625
  },
  "Total" : {
    "transaction" : "Total",
    "sampleCount" : 5,
    "errorCount" : 0,
    "errorPct" : 0.0,
    "meanResTime" : 443.4,
    "medianResTime" : 247.0,
    "minResTime" : 50.0,
    "maxResTime" : 1392.0,
    "pct1ResTime" : 1392.0,
    "pct2ResTime" : 1392.0,
    "pct3ResTime" : 1392.0,
    "throughput" : 2.25022502250225,
    "receivedKBytesPerSec" : 2.9982490436543654,
    "sentKBytesPerSec" : 0.4254331683168317
  },
  "GET - Single User" : {
    "transaction" : "GET - Single User",
    "sampleCount" : 1,
    "errorCount" : 0,
    "errorPct" : 0.0,
    "meanResTime" : 50.0,
    "medianResTime" : 50.0,
    "minResTime" : 50.0,
    "maxResTime" : 50.0,
    "pct1ResTime" : 50.0,
    "pct2ResTime" : 50.0,
    "pct3ResTime" : 50.0,
    "throughput" : 20.0,
    "receivedKBytesPerSec" : 28.41796875,
    "sentKBytesPerSec" : 2.3828125
  }
}